LICENSE
MANIFEST.in
README.md
README.rst
setup.cfg
setup.py
django_perf.egg-info/PKG-INFO
django_perf.egg-info/SOURCES.txt
django_perf.egg-info/dependency_links.txt
django_perf.egg-info/requires.txt
django_perf.egg-info/top_level.txt
perf/__init__.py
perf/middleware.py
perf/network.py
perf/perf.py
perf/recorder.py
perf/request_store.py
tests/__init__.py
tests/tests_middleware.py
tests/tests_recorder.py
tests/tests_request_store.py