Metadata-Version: 1.0
Name: django-perf
Version: 0.2.0
Summary: A simple Django Middleware for sending request data to Perf.
Home-page: https://github.com/perflabs/django-perf
Author: Jonathan Grana
Author-email: john@perf.sh
License: GPL-3.0
Platform: UNKNOWN
